snvmdb/__init__.py
snvmdb/__main__.py
snvmdb/async.py
snvmdb/errors.py
snvmdb/snvmdb.py
snvmdb-1.2.3.dist-info/LICENSE
snvmdb-1.2.3.dist-info/METADATA
snvmdb-1.2.3.dist-info/WHEEL
snvmdb-1.2.3.dist-info/top_level.txt
snvmdb-1.2.3.dist-info/RECORD
