Metadata-Version: 2.1
Name: snvmdb
Version: 1.2.3
Summary: Simple database tool
Home-page: https://github.com/snvmk/snvmdb
Author: SNVMK
Author-email: sidzahroman@gmail.com
License: MIT
Project-URL: Bug Tracker, https://github.com/snvmk/snvmdb/issues
Platform: UNKNOWN
Classifier: Programming Language :: Python :: 3
Classifier: License :: OSI Approved :: MIT License
Classifier: Operating System :: OS Independent
Requires-Python: >=3.5
